README
setup.cfg
setup.py
kerasglove/__init__.py
kerasglove.egg-info/PKG-INFO
kerasglove.egg-info/SOURCES.txt
kerasglove.egg-info/dependency_links.txt
kerasglove.egg-info/top_level.txt