Metadata-Version: 1.1
Name: kerasglove
Version: 1.4
Summary: Pre-trained GLOVE embeddings for keras
Home-page: https://github.com/LukeWoodSMU/KerasGlove
Author: LukeWood
Author-email: lukewoodcs@gmail.com
License: UNKNOWN
Download-URL: https://github.com/LukeWoodSMU/KerasGlove/archive/0.1.tar.gz
Keywords: keras,recurrent,rnn,GLOVE,embedding
Platform: UNKNOWN
